swarmauri_crypto_pgp/PGPCrypto.py
swarmauri_crypto_pgp/__init__.py
swarmauri_crypto_pgp-0.2.0.dev4.dist-info/LICENSE
swarmauri_crypto_pgp-0.2.0.dev4.dist-info/METADATA
swarmauri_crypto_pgp-0.2.0.dev4.dist-info/WHEEL
swarmauri_crypto_pgp-0.2.0.dev4.dist-info/entry_points.txt
swarmauri_crypto_pgp-0.2.0.dev4.dist-info/RECORD
